ai_cost_tracker-0.2.0.dist-info/licenses/LICENSE
openai_cost_tracker/__init__.py
openai_cost_tracker/monitor.py
openai_cost_tracker/cli/__init__.py
openai_cost_tracker/cli/config_email.py
openai_cost_tracker/cli/monitor.py
openai_cost_tracker/cli/scan.py
openai_cost_tracker/cli/view_costs.py
openai_cost_tracker/clients/python_client.py
openai_cost_tracker/services/__init__.py
openai_cost_tracker/services/auto_interceptor.py
openai_cost_tracker/services/cost_tracker.py
openai_cost_tracker/services/email_config.py
openai_cost_tracker/services/network_interceptor.py
openai_cost_tracker/services/openai_scanner.py
openai_cost_tracker/services/system_scanner.py
openai_cost_tracker/services/universal_tracker.py
openai_cost_tracker/services/zero_config_tracker.py
ai_cost_tracker-0.2.0.dist-info/METADATA
ai_cost_tracker-0.2.0.dist-info/WHEEL
ai_cost_tracker-0.2.0.dist-info/entry_points.txt
ai_cost_tracker-0.2.0.dist-info/top_level.txt
ai_cost_tracker-0.2.0.dist-info/RECORD
