Metadata-Version: 2.4
Name: ai-cost-tracker
Version: 0.2.0
Summary: Zero-config OpenAI API cost tracking - just one import and you're done!
Home-page: https://github.com/dhruvildarji/ai-cost-tracker
Author: OpenAI Cost Tracker Contributors
Author-email: 
License: MIT
Keywords: openai,cost,tracking,monitoring,api,usage
Classifier: Development Status :: 4 - Beta
Classifier: Intended Audience :: Developers
Classifier: Programming Language :: Python :: 3
Classifier: Programming Language :: Python :: 3.8
Classifier: Programming Language :: Python :: 3.9
Classifier: Programming Language :: Python :: 3.10
Classifier: Programming Language :: Python :: 3.11
Classifier: Topic :: Software Development :: Libraries :: Python Modules
Classifier: Topic :: System :: Monitoring
Requires-Python: >=3.8
Requires-Dist: openai>=1.0.0
Provides-Extra: email
Requires-Dist: python-dotenv>=1.0.0; extra == "email"
Requires-Dist: requests>=2.28.0; extra == "email"
Provides-Extra: dev
Requires-Dist: pytest>=7.0.0; extra == "dev"
Requires-Dist: black>=23.0.0; extra == "dev"
Requires-Dist: flake8>=6.0.0; extra == "dev"
Dynamic: home-page
Dynamic: requires-python
